ngs_test_utils/__init__.py
ngs_test_utils/base/__init__.py
ngs_test_utils/base/fastq.py
ngs_test_utils/testcase/__init__.py
ngs_test_utils/testcase/bam.py
ngs_test_utils/testcase/bed.py
ngs_test_utils/testcase/fasta.py
ngs_test_utils/testcase/fastq.py
ngs_test_utils/testcase/gtf.py
ngs_test_utils/testcase/tsv.py
ngs_test_utils-0.0.6.dist-info/LICENSE
ngs_test_utils-0.0.6.dist-info/METADATA
ngs_test_utils-0.0.6.dist-info/WHEEL
ngs_test_utils-0.0.6.dist-info/top_level.txt
ngs_test_utils-0.0.6.dist-info/RECORD
