Metadata-Version: 2.1
Name: ngs_test_utils
Version: 0.0.6
Summary: Utilities for generation of synthetic NGS files
Author: Genialis, Inc.
Author-email: info@genialis.com
License: Apache 2.0
Project-URL: repository, https://github.com/genialis/ngs-test-utils
Keywords: ngs,test,bioinformatics
Classifier: Development Status :: 2 - Pre-Alpha
Classifier: Environment :: Console
Classifier: Intended Audience :: Developers
Classifier: Topic :: Software Development :: Libraries :: Python Modules
Classifier: Operating System :: OS Independent
Classifier: Programming Language :: Python
Classifier: Programming Language :: Python :: 3
Classifier: Programming Language :: Python :: 3.11
Classifier: Programming Language :: Python :: 3.12
Requires-Python: <3.13,>=3.11
License-File: LICENSE
Requires-Dist: numpy
Requires-Dist: pybedtools
Requires-Dist: pysam
Provides-Extra: docs
Requires-Dist: sphinx ; extra == 'docs'
Provides-Extra: package
Requires-Dist: build >=0.8.0 ; extra == 'package'
Requires-Dist: check-manifest >=0.48 ; extra == 'package'
Requires-Dist: twine >=4.0.1 ; extra == 'package'
Provides-Extra: test
Requires-Dist: ruff ; extra == 'test'
Requires-Dist: pytest >=7.2.0 ; extra == 'test'
Requires-Dist: pytest-cov >=4.0.0 ; extra == 'test'
Requires-Dist: pytest-mock >=3.10.0 ; extra == 'test'
Requires-Dist: toml >=0.10.2 ; extra == 'test'
